<node>
  <interface name="io.orbitrc.Desktop.Desktop">
    <signal name="numberOfDesktopsChanged" />
    <property name="numberOfDesktops" access="read" type="i" />
    <method name="insertDesktop">
      <arg name="value" direction="in" type="i" />
    </method>
    <method name="removeDesktop">
      <arg name="value" direction="in" type="i" />
    </method>

    <signal name="currentDesktopChanged" />
    <property name="currentDesktop" access="read" type="i" />
    <method name="setCurrentDesktop">
      <arg name="value" direction="in" type="i" />
    </method>
  </interface>
</node>
